PeakPxApi/__init__.py
PeakPxApi-1.0.0.dist-info/METADATA
PeakPxApi-1.0.0.dist-info/WHEEL
PeakPxApi-1.0.0.dist-info/top_level.txt
PeakPxApi-1.0.0.dist-info/RECORD
