Metadata-Version: 2.1
Name: PeakPxApi
Version: 1.0.0
Summary: get/search wallpapers from https://www.peakpx.com/
Home-page: https://github.com/NotStark/PeakPX
Author: notstark
Author-email: YeahAmStark@gmail.com
Classifier: Programming Language :: Python :: 3
Classifier: Programming Language :: Python :: 3.6
Classifier: Programming Language :: Python :: 3.7
Classifier: Programming Language :: Python :: 3.8
Classifier: Programming Language :: Python :: 3.9
Classifier: Operating System :: OS Independent
Requires-Python: >=3.6
Requires-Dist: requests
Requires-Dist: beautifulsoup4
